m5py/__init__.py
m5py/_version.py
m5py/export.py
m5py/linreg_utils.py
m5py/main.py
m5py/py.typed
m5py-0.3.3.dist-info/LICENSE
m5py-0.3.3.dist-info/METADATA
m5py-0.3.3.dist-info/WHEEL
m5py-0.3.3.dist-info/top_level.txt
m5py-0.3.3.dist-info/RECORD
