Metadata-Version: 2.1
Name: m5py
Version: 0.3.3
Summary: An implementation of M5 (Prime) and model trees for scikit-learn.
Home-page: https://github.com/smarie/python-m5p
Download-URL: https://github.com/smarie/python-m5p/tarball/0.3.3
Author: Sylvain MARIE <sylvain.marie@se.com>
Maintainer: Sylvain MARIE <sylvain.marie@se.com>
License: BSD 3-Clause
Keywords: model tree regression M5 prime scikit learn machine learning
Classifier: Development Status :: 5 - Production/Stable
Classifier: Intended Audience :: Developers
Classifier: Intended Audience :: Science/Research
Classifier: License :: OSI Approved :: BSD License
Classifier: Topic :: Software Development :: Libraries :: Python Modules
Classifier: Topic :: Scientific/Engineering :: Mathematics
Classifier: Programming Language :: Python
Classifier: Programming Language :: Python :: 3
Classifier: Programming Language :: Python :: 3.7
Classifier: Programming Language :: Python :: 3.8
Classifier: Programming Language :: Python :: 3.9
License-File: LICENSE
Requires-Dist: scikit-learn
